[{"rt":1379,"stimulus":"Click continue when ready","response":0,"trial_type":"html-button-response","trial_index":0,"time_elapsed":1381,"internal_node_id":"0.0-0.0"},{"rt":null,"stimulus":"+","response":null,"trial_type":"html-keyboard-response","trial_index":1,"time_elapsed":1886,"internal_node_id":"0.0-1.0-0.0"},{"fs":48000,"latency":27.099609375,"f_max":16000,"bin_width":1.46484375,"dummy":27,"file":"../sounds/chirp16.wav","fft_size":2048,"trial_type":"latency-test","trial_index":2,"time_elapsed":6038,"internal_node_id":"0.0-1.0-1.0"},{"rt":null,"stimulus":"+","response":null,"trial_type":"html-keyboard-response","trial_index":3,"time_elapsed":6541,"internal_node_id":"0.0-1.0-0.1"},{"fs":48000,"latency":88.623046875,"f_max":16000,"bin_width":1.46484375,"dummy":88,"file":"../sounds/chirp16.wav","fft_size":2048,"trial_type":"latency-test","trial_index":4,"time_elapsed":10579,"internal_node_id":"0.0-1.0-1.1"},{"rt":null,"stimulus":"+","response":null,"trial_type":"html-keyboard-response","trial_index":5,"time_elapsed":11082,"internal_node_id":"0.0-1.0-0.2"},{"fs":48000,"latency":13.916015625,"f_max":16000,"bin_width":1.46484375,"dummy":13,"file":"../sounds/chirp16.wav","fft_size":2048,"trial_type":"latency-test","trial_index":6,"time_elapsed":15094,"internal_node_id":"0.0-1.0-1.2"},{"rt":null,"stimulus":"+","response":null,"trial_type":"html-keyboard-response","trial_index":7,"time_elapsed":15595,"internal_node_id":"0.0-1.0-0.3"},{"fs":48000,"latency":98.876953125,"f_max":16000,"bin_width":1.46484375,"dummy":98,"file":"../sounds/chirp16.wav","fft_size":2048,"trial_type":"latency-test","trial_index":8,"time_elapsed":19637,"internal_node_id":"0.0-1.0-1.3"},{"rt":null,"stimulus":"+","response":null,"trial_type":"html-keyboard-response","trial_index":9,"time_elapsed":20142,"internal_node_id":"0.0-1.0-0.4"},{"fs":48000,"latency":82.763671875,"f_max":16000,"bin_width":1.46484375,"dummy":83,"file":"../sounds/chirp16.wav","fft_size":2048,"trial_type":"latency-test","trial_index":10,"time_elapsed":24188,"internal_node_id":"0.0-1.0-1.4"},{"rt":null,"stimulus":"+","response":null,"trial_type":"html-keyboard-response","trial_index":11,"time_elapsed":24693,"internal_node_id":"0.0-1.0-0.5"},{"fs":48000,"latency":54.931640625,"f_max":16000,"bin_width":1.46484375,"dummy":54,"file":"../sounds/chirp16.wav","fft_size":2048,"trial_type":"latency-test","trial_index":12,"time_elapsed":28742,"internal_node_id":"0.0-1.0-1.5"},{"rt":null,"stimulus":"+","response":null,"trial_type":"html-keyboard-response","trial_index":13,"time_elapsed":29243,"internal_node_id":"0.0-1.0-0.6"},{"fs":48000,"latency":65.185546875,"f_max":16000,"bin_width":1.46484375,"dummy":64,"file":"../sounds/chirp16.wav","fft_size":2048,"trial_type":"latency-test","trial_index":14,"time_elapsed":33272,"internal_node_id":"0.0-1.0-1.6"},{"rt":null,"stimulus":"+","response":null,"trial_type":"html-keyboard-response","trial_index":15,"time_elapsed":33773,"internal_node_id":"0.0-1.0-0.7"},{"fs":48000,"latency":81.298828125,"f_max":16000,"bin_width":1.46484375,"dummy":80,"file":"../sounds/chirp16.wav","fft_size":2048,"trial_type":"latency-test","trial_index":16,"time_elapsed":37807,"internal_node_id":"0.0-1.0-1.7"},{"rt":null,"stimulus":"+","response":null,"trial_type":"html-keyboard-response","trial_index":17,"time_elapsed":38311,"internal_node_id":"0.0-1.0-0.8"},{"fs":48000,"latency":44.677734375,"f_max":16000,"bin_width":1.46484375,"dummy":44,"file":"../sounds/chirp16.wav","fft_size":2048,"trial_type":"latency-test","trial_index":18,"time_elapsed":42343,"internal_node_id":"0.0-1.0-1.8"},{"rt":null,"stimulus":"+","response":null,"trial_type":"html-keyboard-response","trial_index":19,"time_elapsed":42846,"internal_node_id":"0.0-1.0-0.9"},{"fs":48000,"latency":68.115234375,"f_max":16000,"bin_width":1.46484375,"dummy":68,"file":"../sounds/chirp16.wav","fft_size":2048,"trial_type":"latency-test","trial_index":20,"time_elapsed":46878,"internal_node_id":"0.0-1.0-1.9"},{"rt":null,"stimulus":"+","response":null,"trial_type":"html-keyboard-response","trial_index":21,"time_elapsed":47380,"internal_node_id":"0.0-1.0-0.10"},{"fs":48000,"latency":87.158203125,"f_max":16000,"bin_width":1.46484375,"dummy":87,"file":"../sounds/chirp16.wav","fft_size":2048,"trial_type":"latency-test","trial_index":22,"time_elapsed":51410,"internal_node_id":"0.0-1.0-1.10"},{"rt":null,"stimulus":"+","response":null,"trial_type":"html-keyboard-response","trial_index":23,"time_elapsed":51913,"internal_node_id":"0.0-1.0-0.11"},{"fs":48000,"latency":13.916015625,"f_max":16000,"bin_width":1.46484375,"dummy":14,"file":"../sounds/chirp16.wav","fft_size":2048,"trial_type":"latency-test","trial_index":24,"time_elapsed":55922,"internal_node_id":"0.0-1.0-1.11"},{"rt":null,"stimulus":"+","response":null,"trial_type":"html-keyboard-response","trial_index":25,"time_elapsed":56424,"internal_node_id":"0.0-1.0-0.12"},{"fs":48000,"latency":40.283203125,"f_max":16000,"bin_width":1.46484375,"dummy":40,"file":"../sounds/chirp16.wav","fft_size":2048,"trial_type":"latency-test","trial_index":26,"time_elapsed":60437,"internal_node_id":"0.0-1.0-1.12"},{"rt":null,"stimulus":"+","response":null,"trial_type":"html-keyboard-response","trial_index":27,"time_elapsed":60942,"internal_node_id":"0.0-1.0-0.13"},{"fs":48000,"latency":32.958984375,"f_max":16000,"bin_width":1.46484375,"dummy":32,"file":"../sounds/chirp16.wav","fft_size":2048,"trial_type":"latency-test","trial_index":28,"time_elapsed":64954,"internal_node_id":"0.0-1.0-1.13"},{"rt":null,"stimulus":"+","response":null,"trial_type":"html-keyboard-response","trial_index":29,"time_elapsed":65458,"internal_node_id":"0.0-1.0-0.14"},{"fs":48000,"latency":10.986328125,"f_max":16000,"bin_width":1.46484375,"dummy":11,"file":"../sounds/chirp16.wav","fft_size":2048,"trial_type":"latency-test","trial_index":30,"time_elapsed":69470,"internal_node_id":"0.0-1.0-1.14"},{"rt":null,"stimulus":"+","response":null,"trial_type":"html-keyboard-response","trial_index":31,"time_elapsed":69970,"internal_node_id":"0.0-1.0-0.15"},{"fs":48000,"latency":90.087890625,"f_max":16000,"bin_width":1.46484375,"dummy":89,"file":"../sounds/chirp16.wav","fft_size":2048,"trial_type":"latency-test","trial_index":32,"time_elapsed":74016,"internal_node_id":"0.0-1.0-1.15"},{"rt":null,"stimulus":"+","response":null,"trial_type":"html-keyboard-response","trial_index":33,"time_elapsed":74519,"internal_node_id":"0.0-1.0-0.16"},{"fs":48000,"latency":57.861328125,"f_max":16000,"bin_width":1.46484375,"dummy":57,"file":"../sounds/chirp16.wav","fft_size":2048,"trial_type":"latency-test","trial_index":34,"time_elapsed":78534,"internal_node_id":"0.0-1.0-1.16"},{"rt":null,"stimulus":"+","response":null,"trial_type":"html-keyboard-response","trial_index":35,"time_elapsed":79038,"internal_node_id":"0.0-1.0-0.17"},{"fs":48000,"latency":34.423828125,"f_max":16000,"bin_width":1.46484375,"dummy":34,"file":"../sounds/chirp16.wav","fft_size":2048,"trial_type":"latency-test","trial_index":36,"time_elapsed":83083,"internal_node_id":"0.0-1.0-1.17"},{"rt":null,"stimulus":"+","response":null,"trial_type":"html-keyboard-response","trial_index":37,"time_elapsed":83588,"internal_node_id":"0.0-1.0-0.18"},{"fs":48000,"latency":59.326171875,"f_max":16000,"bin_width":1.46484375,"dummy":59,"file":"../sounds/chirp16.wav","fft_size":2048,"trial_type":"latency-test","trial_index":38,"time_elapsed":87635,"internal_node_id":"0.0-1.0-1.18"},{"rt":null,"stimulus":"+","response":null,"trial_type":"html-keyboard-response","trial_index":39,"time_elapsed":88139,"internal_node_id":"0.0-1.0-0.19"},{"fs":48000,"latency":97.412109375,"f_max":16000,"bin_width":1.46484375,"dummy":97,"file":"../sounds/chirp16.wav","fft_size":2048,"trial_type":"latency-test","trial_index":40,"time_elapsed":92171,"internal_node_id":"0.0-1.0-1.19"},{"rt":null,"stimulus":"+","response":null,"trial_type":"html-keyboard-response","trial_index":41,"time_elapsed":92676,"internal_node_id":"0.0-1.0-0.20"},{"fs":48000,"latency":21.240234375,"f_max":16000,"bin_width":1.46484375,"dummy":21,"file":"../sounds/chirp16.wav","fft_size":2048,"trial_type":"latency-test","trial_index":42,"time_elapsed":96724,"internal_node_id":"0.0-1.0-1.20"},{"rt":null,"stimulus":"+","response":null,"trial_type":"html-keyboard-response","trial_index":43,"time_elapsed":97224,"internal_node_id":"0.0-1.0-0.21"},{"fs":48000,"latency":19.775390625,"f_max":16000,"bin_width":1.46484375,"dummy":20,"file":"../sounds/chirp16.wav","fft_size":2048,"trial_type":"latency-test","trial_index":44,"time_elapsed":101239,"internal_node_id":"0.0-1.0-1.21"},{"rt":null,"stimulus":"+","response":null,"trial_type":"html-keyboard-response","trial_index":45,"time_elapsed":101744,"internal_node_id":"0.0-1.0-0.22"},{"fs":48000,"latency":81.298828125,"f_max":16000,"bin_width":1.46484375,"dummy":81,"file":"../sounds/chirp16.wav","fft_size":2048,"trial_type":"latency-test","trial_index":46,"time_elapsed":105790,"internal_node_id":"0.0-1.0-1.22"},{"rt":null,"stimulus":"+","response":null,"trial_type":"html-keyboard-response","trial_index":47,"time_elapsed":106295,"internal_node_id":"0.0-1.0-0.23"},{"fs":48000,"latency":52.001953125,"f_max":16000,"bin_width":1.46484375,"dummy":51,"file":"../sounds/chirp16.wav","fft_size":2048,"trial_type":"latency-test","trial_index":48,"time_elapsed":110310,"internal_node_id":"0.0-1.0-1.23"},{"rt":null,"stimulus":"+","response":null,"trial_type":"html-keyboard-response","trial_index":49,"time_elapsed":110810,"internal_node_id":"0.0-1.0-0.24"},{"fs":48000,"latency":73.974609375,"f_max":16000,"bin_width":1.46484375,"dummy":74,"file":"../sounds/chirp16.wav","fft_size":2048,"trial_type":"latency-test","trial_index":50,"time_elapsed":114824,"internal_node_id":"0.0-1.0-1.24"},{"rt":null,"stimulus":"+","response":null,"trial_type":"html-keyboard-response","trial_index":51,"time_elapsed":115325,"internal_node_id":"0.0-1.0-0.25"},{"fs":48000,"latency":78.369140625,"f_max":16000,"bin_width":1.46484375,"dummy":78,"file":"../sounds/chirp16.wav","fft_size":2048,"trial_type":"latency-test","trial_index":52,"time_elapsed":119363,"internal_node_id":"0.0-1.0-1.25"},{"rt":null,"stimulus":"+","response":null,"trial_type":"html-keyboard-response","trial_index":53,"time_elapsed":119864,"internal_node_id":"0.0-1.0-0.26"},{"fs":48000,"latency":38.818359375,"f_max":16000,"bin_width":1.46484375,"dummy":39,"file":"../sounds/chirp16.wav","fft_size":2048,"trial_type":"latency-test","trial_index":54,"time_elapsed":123882,"internal_node_id":"0.0-1.0-1.26"},{"rt":null,"stimulus":"+","response":null,"trial_type":"html-keyboard-response","trial_index":55,"time_elapsed":124383,"internal_node_id":"0.0-1.0-0.27"},{"fs":48000,"latency":9.521484375,"f_max":16000,"bin_width":1.46484375,"dummy":9,"file":"../sounds/chirp16.wav","fft_size":2048,"trial_type":"latency-test","trial_index":56,"time_elapsed":128429,"internal_node_id":"0.0-1.0-1.27"},{"rt":null,"stimulus":"+","response":null,"trial_type":"html-keyboard-response","trial_index":57,"time_elapsed":128931,"internal_node_id":"0.0-1.0-0.28"},{"fs":48000,"latency":69.580078125,"f_max":16000,"bin_width":1.46484375,"dummy":69,"file":"../sounds/chirp16.wav","fft_size":2048,"trial_type":"latency-test","trial_index":58,"time_elapsed":132940,"internal_node_id":"0.0-1.0-1.28"},{"rt":null,"stimulus":"+","response":null,"trial_type":"html-keyboard-response","trial_index":59,"time_elapsed":133443,"internal_node_id":"0.0-1.0-0.29"},{"fs":48000,"latency":46.142578125,"f_max":16000,"bin_width":1.46484375,"dummy":46,"file":"../sounds/chirp16.wav","fft_size":2048,"trial_type":"latency-test","trial_index":60,"time_elapsed":137450,"internal_node_id":"0.0-1.0-1.29"},{"rt":null,"stimulus":"+","response":null,"trial_type":"html-keyboard-response","trial_index":61,"time_elapsed":137953,"internal_node_id":"0.0-1.0-0.30"},{"fs":48000,"latency":50.537109375,"f_max":16000,"bin_width":1.46484375,"dummy":50,"file":"../sounds/chirp16.wav","fft_size":2048,"trial_type":"latency-test","trial_index":62,"time_elapsed":141999,"internal_node_id":"0.0-1.0-1.30"},{"rt":null,"stimulus":"+","response":null,"trial_type":"html-keyboard-response","trial_index":63,"time_elapsed":142504,"internal_node_id":"0.0-1.0-0.31"},{"fs":48000,"latency":28.564453125,"f_max":16000,"bin_width":1.46484375,"dummy":28,"file":"../sounds/chirp16.wav","fft_size":2048,"trial_type":"latency-test","trial_index":64,"time_elapsed":146530,"internal_node_id":"0.0-1.0-1.31"},{"rt":null,"stimulus":"+","response":null,"trial_type":"html-keyboard-response","trial_index":65,"time_elapsed":147031,"internal_node_id":"0.0-1.0-0.32"},{"fs":48000,"latency":75.439453125,"f_max":16000,"bin_width":1.46484375,"dummy":75,"file":"../sounds/chirp16.wav","fft_size":2048,"trial_type":"latency-test","trial_index":66,"time_elapsed":151049,"internal_node_id":"0.0-1.0-1.32"},{"rt":null,"stimulus":"+","response":null,"trial_type":"html-keyboard-response","trial_index":67,"time_elapsed":151554,"internal_node_id":"0.0-1.0-0.33"},{"fs":48000,"latency":59.326171875,"f_max":16000,"bin_width":1.46484375,"dummy":58,"file":"../sounds/chirp16.wav","fft_size":2048,"trial_type":"latency-test","trial_index":68,"time_elapsed":155603,"internal_node_id":"0.0-1.0-1.33"},{"rt":null,"stimulus":"+","response":null,"trial_type":"html-keyboard-response","trial_index":69,"time_elapsed":156108,"internal_node_id":"0.0-1.0-0.34"},{"fs":48000,"latency":63.720703125,"f_max":16000,"bin_width":1.46484375,"dummy":63,"file":"../sounds/chirp16.wav","fft_size":2048,"trial_type":"latency-test","trial_index":70,"time_elapsed":160120,"internal_node_id":"0.0-1.0-1.34"},{"rt":null,"stimulus":"+","response":null,"trial_type":"html-keyboard-response","trial_index":71,"time_elapsed":160625,"internal_node_id":"0.0-1.0-0.35"},{"fs":48000,"latency":41.748046875,"f_max":16000,"bin_width":1.46484375,"dummy":41,"file":"../sounds/chirp16.wav","fft_size":2048,"trial_type":"latency-test","trial_index":72,"time_elapsed":164639,"internal_node_id":"0.0-1.0-1.35"},{"rt":null,"stimulus":"+","response":null,"trial_type":"html-keyboard-response","trial_index":73,"time_elapsed":165143,"internal_node_id":"0.0-1.0-0.36"},{"fs":48000,"latency":49.072265625,"f_max":16000,"bin_width":1.46484375,"dummy":48,"file":"../sounds/chirp16.wav","fft_size":2048,"trial_type":"latency-test","trial_index":74,"time_elapsed":169172,"internal_node_id":"0.0-1.0-1.36"},{"rt":null,"stimulus":"+","response":null,"trial_type":"html-keyboard-response","trial_index":75,"time_elapsed":169673,"internal_node_id":"0.0-1.0-0.37"},{"fs":48000,"latency":54.931640625,"f_max":16000,"bin_width":1.46484375,"dummy":55,"file":"../sounds/chirp16.wav","fft_size":2048,"trial_type":"latency-test","trial_index":76,"time_elapsed":173707,"internal_node_id":"0.0-1.0-1.37"},{"rt":null,"stimulus":"+","response":null,"trial_type":"html-keyboard-response","trial_index":77,"time_elapsed":174210,"internal_node_id":"0.0-1.0-0.38"},{"fs":48000,"latency":25.634765625,"f_max":16000,"bin_width":1.46484375,"dummy":25,"file":"../sounds/chirp16.wav","fft_size":2048,"trial_type":"latency-test","trial_index":78,"time_elapsed":178221,"internal_node_id":"0.0-1.0-1.38"},{"rt":null,"stimulus":"+","response":null,"trial_type":"html-keyboard-response","trial_index":79,"time_elapsed":178722,"internal_node_id":"0.0-1.0-0.39"},{"fs":48000,"latency":6.591796875,"f_max":16000,"bin_width":1.46484375,"dummy":6,"file":"../sounds/chirp16.wav","fft_size":2048,"trial_type":"latency-test","trial_index":80,"time_elapsed":182734,"internal_node_id":"0.0-1.0-1.39"},{"rt":null,"stimulus":"+","response":null,"trial_type":"html-keyboard-response","trial_index":81,"time_elapsed":183238,"internal_node_id":"0.0-1.0-0.40"},{"fs":48000,"latency":35.888671875,"f_max":16000,"bin_width":1.46484375,"dummy":35,"file":"../sounds/chirp16.wav","fft_size":2048,"trial_type":"latency-test","trial_index":82,"time_elapsed":187261,"internal_node_id":"0.0-1.0-1.40"},{"rt":null,"stimulus":"+","response":null,"trial_type":"html-keyboard-response","trial_index":83,"time_elapsed":187762,"internal_node_id":"0.0-1.0-0.41"},{"fs":48000,"latency":100.341796875,"f_max":16000,"bin_width":1.46484375,"dummy":99,"file":"../sounds/chirp16.wav","fft_size":2048,"trial_type":"latency-test","trial_index":84,"time_elapsed":191812,"internal_node_id":"0.0-1.0-1.41"},{"rt":null,"stimulus":"+","response":null,"trial_type":"html-keyboard-response","trial_index":85,"time_elapsed":192316,"internal_node_id":"0.0-1.0-0.42"},{"fs":48000,"latency":85.693359375,"f_max":16000,"bin_width":1.46484375,"dummy":85,"file":"../sounds/chirp16.wav","fft_size":2048,"trial_type":"latency-test","trial_index":86,"time_elapsed":196343,"internal_node_id":"0.0-1.0-1.42"},{"rt":null,"stimulus":"+","response":null,"trial_type":"html-keyboard-response","trial_index":87,"time_elapsed":196845,"internal_node_id":"0.0-1.0-0.43"},{"fs":48000,"latency":37.353515625,"f_max":16000,"bin_width":1.46484375,"dummy":36,"file":"../sounds/chirp16.wav","fft_size":2048,"trial_type":"latency-test","trial_index":88,"time_elapsed":200883,"internal_node_id":"0.0-1.0-1.43"},{"rt":null,"stimulus":"+","response":null,"trial_type":"html-keyboard-response","trial_index":89,"time_elapsed":201384,"internal_node_id":"0.0-1.0-0.44"},{"fs":48000,"latency":82.763671875,"f_max":16000,"bin_width":1.46484375,"dummy":82,"file":"../sounds/chirp16.wav","fft_size":2048,"trial_type":"latency-test","trial_index":90,"time_elapsed":205432,"internal_node_id":"0.0-1.0-1.44"},{"rt":null,"stimulus":"+","response":null,"trial_type":"html-keyboard-response","trial_index":91,"time_elapsed":205935,"internal_node_id":"0.0-1.0-0.45"},{"fs":48000,"latency":71.044921875,"f_max":16000,"bin_width":1.46484375,"dummy":71,"file":"../sounds/chirp16.wav","fft_size":2048,"trial_type":"latency-test","trial_index":92,"time_elapsed":209942,"internal_node_id":"0.0-1.0-1.45"},{"rt":null,"stimulus":"+","response":null,"trial_type":"html-keyboard-response","trial_index":93,"time_elapsed":210443,"internal_node_id":"0.0-1.0-0.46"},{"fs":48000,"latency":3.662109375,"f_max":16000,"bin_width":1.46484375,"dummy":4,"file":"../sounds/chirp16.wav","fft_size":2048,"trial_type":"latency-test","trial_index":94,"time_elapsed":214463,"internal_node_id":"0.0-1.0-1.46"},{"rt":null,"stimulus":"+","response":null,"trial_type":"html-keyboard-response","trial_index":95,"time_elapsed":214963,"internal_node_id":"0.0-1.0-0.47"},{"fs":48000,"latency":2.197265625,"f_max":16000,"bin_width":1.46484375,"dummy":2,"file":"../sounds/chirp16.wav","fft_size":2048,"trial_type":"latency-test","trial_index":96,"time_elapsed":218984,"internal_node_id":"0.0-1.0-1.47"},{"rt":null,"stimulus":"+","response":null,"trial_type":"html-keyboard-response","trial_index":97,"time_elapsed":219487,"internal_node_id":"0.0-1.0-0.48"},{"fs":48000,"latency":95.947265625,"f_max":16000,"bin_width":1.46484375,"dummy":96,"file":"../sounds/chirp16.wav","fft_size":2048,"trial_type":"latency-test","trial_index":98,"time_elapsed":223521,"internal_node_id":"0.0-1.0-1.48"},{"rt":null,"stimulus":"+","response":null,"trial_type":"html-keyboard-response","trial_index":99,"time_elapsed":224023,"internal_node_id":"0.0-1.0-0.49"},{"fs":48000,"latency":3.662109375,"f_max":16000,"bin_width":1.46484375,"dummy":3,"file":"../sounds/chirp16.wav","fft_size":2048,"trial_type":"latency-test","trial_index":100,"time_elapsed":228072,"internal_node_id":"0.0-1.0-1.49"},{"rt":null,"stimulus":"+","response":null,"trial_type":"html-keyboard-response","trial_index":101,"time_elapsed":228577,"internal_node_id":"0.0-1.0-0.50"},{"fs":48000,"latency":66.650390625,"f_max":16000,"bin_width":1.46484375,"dummy":66,"file":"../sounds/chirp16.wav","fft_size":2048,"trial_type":"latency-test","trial_index":102,"time_elapsed":232585,"internal_node_id":"0.0-1.0-1.50"},{"rt":null,"stimulus":"+","response":null,"trial_type":"html-keyboard-response","trial_index":103,"time_elapsed":233086,"internal_node_id":"0.0-1.0-0.51"},{"fs":48000,"latency":46.142578125,"f_max":16000,"bin_width":1.46484375,"dummy":45,"file":"../sounds/chirp16.wav","fft_size":2048,"trial_type":"latency-test","trial_index":104,"time_elapsed":237107,"internal_node_id":"0.0-1.0-1.51"},{"rt":null,"stimulus":"+","response":null,"trial_type":"html-keyboard-response","trial_index":105,"time_elapsed":237610,"internal_node_id":"0.0-1.0-0.52"},{"fs":48000,"latency":2.197265625,"f_max":16000,"bin_width":1.46484375,"dummy":1,"file":"../sounds/chirp16.wav","fft_size":2048,"trial_type":"latency-test","trial_index":106,"time_elapsed":241638,"internal_node_id":"0.0-1.0-1.52"},{"rt":null,"stimulus":"+","response":null,"trial_type":"html-keyboard-response","trial_index":107,"time_elapsed":242138,"internal_node_id":"0.0-1.0-0.53"},{"fs":48000,"latency":53.466796875,"f_max":16000,"bin_width":1.46484375,"dummy":53,"file":"../sounds/chirp16.wav","fft_size":2048,"trial_type":"latency-test","trial_index":108,"time_elapsed":246150,"internal_node_id":"0.0-1.0-1.53"},{"rt":null,"stimulus":"+","response":null,"trial_type":"html-keyboard-response","trial_index":109,"time_elapsed":246652,"internal_node_id":"0.0-1.0-0.54"},{"fs":48000,"latency":93.017578125,"f_max":16000,"bin_width":1.46484375,"dummy":93,"file":"../sounds/chirp16.wav","fft_size":2048,"trial_type":"latency-test","trial_index":110,"time_elapsed":250693,"internal_node_id":"0.0-1.0-1.54"},{"rt":null,"stimulus":"+","response":null,"trial_type":"html-keyboard-response","trial_index":111,"time_elapsed":251194,"internal_node_id":"0.0-1.0-0.55"},{"fs":48000,"latency":68.115234375,"f_max":16000,"bin_width":1.46484375,"dummy":67,"file":"../sounds/chirp16.wav","fft_size":2048,"trial_type":"latency-test","trial_index":112,"time_elapsed":255201,"internal_node_id":"0.0-1.0-1.55"},{"rt":null,"stimulus":"+","response":null,"trial_type":"html-keyboard-response","trial_index":113,"time_elapsed":255702,"internal_node_id":"0.0-1.0-0.56"},{"fs":48000,"latency":43.212890625,"f_max":16000,"bin_width":1.46484375,"dummy":42,"file":"../sounds/chirp16.wav","fft_size":2048,"trial_type":"latency-test","trial_index":114,"time_elapsed":259731,"internal_node_id":"0.0-1.0-1.56"},{"rt":null,"stimulus":"+","response":null,"trial_type":"html-keyboard-response","trial_index":115,"time_elapsed":260231,"internal_node_id":"0.0-1.0-0.57"},{"fs":48000,"latency":43.212890625,"f_max":16000,"bin_width":1.46484375,"dummy":43,"file":"../sounds/chirp16.wav","fft_size":2048,"trial_type":"latency-test","trial_index":116,"time_elapsed":264264,"internal_node_id":"0.0-1.0-1.57"},{"rt":null,"stimulus":"+","response":null,"trial_type":"html-keyboard-response","trial_index":117,"time_elapsed":264766,"internal_node_id":"0.0-1.0-0.58"},{"fs":48000,"latency":24.169921875,"f_max":16000,"bin_width":1.46484375,"dummy":23,"file":"../sounds/chirp16.wav","fft_size":2048,"trial_type":"latency-test","trial_index":118,"time_elapsed":268782,"internal_node_id":"0.0-1.0-1.58"},{"rt":null,"stimulus":"+","response":null,"trial_type":"html-keyboard-response","trial_index":119,"time_elapsed":269285,"internal_node_id":"0.0-1.0-0.59"},{"fs":48000,"latency":47.607421875,"f_max":16000,"bin_width":1.46484375,"dummy":47,"file":"../sounds/chirp16.wav","fft_size":2048,"trial_type":"latency-test","trial_index":120,"time_elapsed":273318,"internal_node_id":"0.0-1.0-1.59"},{"rt":null,"stimulus":"+","response":null,"trial_type":"html-keyboard-response","trial_index":121,"time_elapsed":273819,"internal_node_id":"0.0-1.0-0.60"},{"fs":48000,"latency":5.126953125,"f_max":16000,"bin_width":1.46484375,"dummy":5,"file":"../sounds/chirp16.wav","fft_size":2048,"trial_type":"latency-test","trial_index":122,"time_elapsed":277849,"internal_node_id":"0.0-1.0-1.60"},{"rt":null,"stimulus":"+","response":null,"trial_type":"html-keyboard-response","trial_index":123,"time_elapsed":278354,"internal_node_id":"0.0-1.0-0.61"},{"fs":48000,"latency":6.591796875,"f_max":16000,"bin_width":1.46484375,"dummy":7,"file":"../sounds/chirp16.wav","fft_size":2048,"trial_type":"latency-test","trial_index":124,"time_elapsed":282371,"internal_node_id":"0.0-1.0-1.61"},{"rt":null,"stimulus":"+","response":null,"trial_type":"html-keyboard-response","trial_index":125,"time_elapsed":282871,"internal_node_id":"0.0-1.0-0.62"},{"fs":48000,"latency":87.158203125,"f_max":16000,"bin_width":1.46484375,"dummy":86,"file":"../sounds/chirp16.wav","fft_size":2048,"trial_type":"latency-test","trial_index":126,"time_elapsed":286888,"internal_node_id":"0.0-1.0-1.62"},{"rt":null,"stimulus":"+","response":null,"trial_type":"html-keyboard-response","trial_index":127,"time_elapsed":287392,"internal_node_id":"0.0-1.0-0.63"},{"fs":48000,"latency":49.072265625,"f_max":16000,"bin_width":1.46484375,"dummy":49,"file":"../sounds/chirp16.wav","fft_size":2048,"trial_type":"latency-test","trial_index":128,"time_elapsed":291437,"internal_node_id":"0.0-1.0-1.63"},{"rt":null,"stimulus":"+","response":null,"trial_type":"html-keyboard-response","trial_index":129,"time_elapsed":291940,"internal_node_id":"0.0-1.0-0.64"},{"fs":48000,"latency":72.509765625,"f_max":16000,"bin_width":1.46484375,"dummy":72,"file":"../sounds/chirp16.wav","fft_size":2048,"trial_type":"latency-test","trial_index":130,"time_elapsed":295986,"internal_node_id":"0.0-1.0-1.64"},{"rt":null,"stimulus":"+","response":null,"trial_type":"html-keyboard-response","trial_index":131,"time_elapsed":296491,"internal_node_id":"0.0-1.0-0.65"},{"fs":48000,"latency":56.396484375,"f_max":16000,"bin_width":1.46484375,"dummy":56,"file":"../sounds/chirp16.wav","fft_size":2048,"trial_type":"latency-test","trial_index":132,"time_elapsed":300507,"internal_node_id":"0.0-1.0-1.65"},{"rt":null,"stimulus":"+","response":null,"trial_type":"html-keyboard-response","trial_index":133,"time_elapsed":301012,"internal_node_id":"0.0-1.0-0.66"},{"fs":48000,"latency":95.947265625,"f_max":16000,"bin_width":1.46484375,"dummy":95,"file":"../sounds/chirp16.wav","fft_size":2048,"trial_type":"latency-test","trial_index":134,"time_elapsed":305057,"internal_node_id":"0.0-1.0-1.66"},{"rt":null,"stimulus":"+","response":null,"trial_type":"html-keyboard-response","trial_index":135,"time_elapsed":305559,"internal_node_id":"0.0-1.0-0.67"},{"fs":48000,"latency":79.833984375,"f_max":16000,"bin_width":1.46484375,"dummy":79,"file":"../sounds/chirp16.wav","fft_size":2048,"trial_type":"latency-test","trial_index":136,"time_elapsed":309573,"internal_node_id":"0.0-1.0-1.67"},{"rt":null,"stimulus":"+","response":null,"trial_type":"html-keyboard-response","trial_index":137,"time_elapsed":310082,"internal_node_id":"0.0-1.0-0.68"},{"fs":48000,"latency":12.451171875,"f_max":16000,"bin_width":1.46484375,"dummy":12,"file":"../sounds/chirp16.wav","fft_size":2048,"trial_type":"latency-test","trial_index":138,"time_elapsed":314123,"internal_node_id":"0.0-1.0-1.68"},{"rt":null,"stimulus":"+","response":null,"trial_type":"html-keyboard-response","trial_index":139,"time_elapsed":314625,"internal_node_id":"0.0-1.0-0.69"},{"fs":48000,"latency":60.791015625,"f_max":16000,"bin_width":1.46484375,"dummy":60,"file":"../sounds/chirp16.wav","fft_size":2048,"trial_type":"latency-test","trial_index":140,"time_elapsed":318675,"internal_node_id":"0.0-1.0-1.69"},{"rt":null,"stimulus":"+","response":null,"trial_type":"html-keyboard-response","trial_index":141,"time_elapsed":319180,"internal_node_id":"0.0-1.0-0.70"},{"fs":48000,"latency":18.310546875,"f_max":16000,"bin_width":1.46484375,"dummy":18,"file":"../sounds/chirp16.wav","fft_size":2048,"trial_type":"latency-test","trial_index":142,"time_elapsed":323223,"internal_node_id":"0.0-1.0-1.70"},{"rt":null,"stimulus":"+","response":null,"trial_type":"html-keyboard-response","trial_index":143,"time_elapsed":323723,"internal_node_id":"0.0-1.0-0.71"},{"fs":48000,"latency":18.310546875,"f_max":16000,"bin_width":1.46484375,"dummy":17,"file":"../sounds/chirp16.wav","fft_size":2048,"trial_type":"latency-test","trial_index":144,"time_elapsed":327759,"internal_node_id":"0.0-1.0-1.71"},{"rt":null,"stimulus":"+","response":null,"trial_type":"html-keyboard-response","trial_index":145,"time_elapsed":328265,"internal_node_id":"0.0-1.0-0.72"},{"fs":48000,"latency":30.029296875,"f_max":16000,"bin_width":1.46484375,"dummy":29,"file":"../sounds/chirp16.wav","fft_size":2048,"trial_type":"latency-test","trial_index":146,"time_elapsed":332272,"internal_node_id":"0.0-1.0-1.72"},{"rt":null,"stimulus":"+","response":null,"trial_type":"html-keyboard-response","trial_index":147,"time_elapsed":332779,"internal_node_id":"0.0-1.0-0.73"},{"fs":48000,"latency":65.185546875,"f_max":16000,"bin_width":1.46484375,"dummy":65,"file":"../sounds/chirp16.wav","fft_size":2048,"trial_type":"latency-test","trial_index":148,"time_elapsed":336797,"internal_node_id":"0.0-1.0-1.73"},{"rt":null,"stimulus":"+","response":null,"trial_type":"html-keyboard-response","trial_index":149,"time_elapsed":337301,"internal_node_id":"0.0-1.0-0.74"},{"fs":48000,"latency":90.087890625,"f_max":16000,"bin_width":1.46484375,"dummy":90,"file":"../sounds/chirp16.wav","fft_size":2048,"trial_type":"latency-test","trial_index":150,"time_elapsed":341310,"internal_node_id":"0.0-1.0-1.74"},{"rt":null,"stimulus":"+","response":null,"trial_type":"html-keyboard-response","trial_index":151,"time_elapsed":341813,"internal_node_id":"0.0-1.0-0.75"},{"fs":48000,"latency":24.169921875,"f_max":16000,"bin_width":1.46484375,"dummy":24,"file":"../sounds/chirp16.wav","fft_size":2048,"trial_type":"latency-test","trial_index":152,"time_elapsed":345868,"internal_node_id":"0.0-1.0-1.75"},{"rt":null,"stimulus":"+","response":null,"trial_type":"html-keyboard-response","trial_index":153,"time_elapsed":346373,"internal_node_id":"0.0-1.0-0.76"},{"fs":48000,"latency":91.552734375,"f_max":16000,"bin_width":1.46484375,"dummy":91,"file":"../sounds/chirp16.wav","fft_size":2048,"trial_type":"latency-test","trial_index":154,"time_elapsed":350396,"internal_node_id":"0.0-1.0-1.76"},{"rt":null,"stimulus":"+","response":null,"trial_type":"html-keyboard-response","trial_index":155,"time_elapsed":350897,"internal_node_id":"0.0-1.0-0.77"},{"fs":48000,"latency":93.017578125,"f_max":16000,"bin_width":1.46484375,"dummy":92,"file":"../sounds/chirp16.wav","fft_size":2048,"trial_type":"latency-test","trial_index":156,"time_elapsed":354910,"internal_node_id":"0.0-1.0-1.77"},{"rt":null,"stimulus":"+","response":null,"trial_type":"html-keyboard-response","trial_index":157,"time_elapsed":355421,"internal_node_id":"0.0-1.0-0.78"},{"fs":48000,"latency":52.001953125,"f_max":16000,"bin_width":1.46484375,"dummy":52,"file":"../sounds/chirp16.wav","fft_size":2048,"trial_type":"latency-test","trial_index":158,"time_elapsed":359432,"internal_node_id":"0.0-1.0-1.78"},{"rt":null,"stimulus":"+","response":null,"trial_type":"html-keyboard-response","trial_index":159,"time_elapsed":359938,"internal_node_id":"0.0-1.0-0.79"},{"fs":48000,"latency":38.818359375,"f_max":16000,"bin_width":1.46484375,"dummy":38,"file":"../sounds/chirp16.wav","fft_size":2048,"trial_type":"latency-test","trial_index":160,"time_elapsed":363955,"internal_node_id":"0.0-1.0-1.79"},{"rt":null,"stimulus":"+","response":null,"trial_type":"html-keyboard-response","trial_index":161,"time_elapsed":364457,"internal_node_id":"0.0-1.0-0.80"},{"fs":48000,"latency":73.974609375,"f_max":16000,"bin_width":1.46484375,"dummy":73,"file":"../sounds/chirp16.wav","fft_size":2048,"trial_type":"latency-test","trial_index":162,"time_elapsed":368487,"internal_node_id":"0.0-1.0-1.80"},{"rt":null,"stimulus":"+","response":null,"trial_type":"html-keyboard-response","trial_index":163,"time_elapsed":368992,"internal_node_id":"0.0-1.0-0.81"},{"fs":48000,"latency":78.369140625,"f_max":16000,"bin_width":1.46484375,"dummy":77,"file":"../sounds/chirp16.wav","fft_size":2048,"trial_type":"latency-test","trial_index":164,"time_elapsed":373017,"internal_node_id":"0.0-1.0-1.81"},{"rt":null,"stimulus":"+","response":null,"trial_type":"html-keyboard-response","trial_index":165,"time_elapsed":373518,"internal_node_id":"0.0-1.0-0.82"},{"fs":48000,"latency":32.958984375,"f_max":16000,"bin_width":1.46484375,"dummy":33,"file":"../sounds/chirp16.wav","fft_size":2048,"trial_type":"latency-test","trial_index":166,"time_elapsed":377558,"internal_node_id":"0.0-1.0-1.82"},{"rt":null,"stimulus":"+","response":null,"trial_type":"html-keyboard-response","trial_index":167,"time_elapsed":378067,"internal_node_id":"0.0-1.0-0.83"},{"fs":48000,"latency":16.845703125,"f_max":16000,"bin_width":1.46484375,"dummy":16,"file":"../sounds/chirp16.wav","fft_size":2048,"trial_type":"latency-test","trial_index":168,"time_elapsed":382107,"internal_node_id":"0.0-1.0-1.83"},{"rt":null,"stimulus":"+","response":null,"trial_type":"html-keyboard-response","trial_index":169,"time_elapsed":382612,"internal_node_id":"0.0-1.0-0.84"},{"fs":48000,"latency":94.482421875,"f_max":16000,"bin_width":1.46484375,"dummy":94,"file":"../sounds/chirp16.wav","fft_size":2048,"trial_type":"latency-test","trial_index":170,"time_elapsed":386638,"internal_node_id":"0.0-1.0-1.84"},{"rt":null,"stimulus":"+","response":null,"trial_type":"html-keyboard-response","trial_index":171,"time_elapsed":387145,"internal_node_id":"0.0-1.0-0.85"},{"fs":48000,"latency":22.705078125,"f_max":16000,"bin_width":1.46484375,"dummy":22,"file":"../sounds/chirp16.wav","fft_size":2048,"trial_type":"latency-test","trial_index":172,"time_elapsed":391174,"internal_node_id":"0.0-1.0-1.85"},{"rt":null,"stimulus":"+","response":null,"trial_type":"html-keyboard-response","trial_index":173,"time_elapsed":391675,"internal_node_id":"0.0-1.0-0.86"},{"fs":48000,"latency":37.353515625,"f_max":16000,"bin_width":1.46484375,"dummy":37,"file":"../sounds/chirp16.wav","fft_size":2048,"trial_type":"latency-test","trial_index":174,"time_elapsed":395706,"internal_node_id":"0.0-1.0-1.86"},{"rt":null,"stimulus":"+","response":null,"trial_type":"html-keyboard-response","trial_index":175,"time_elapsed":396211,"internal_node_id":"0.0-1.0-0.87"},{"fs":48000,"latency":15.380859375,"f_max":16000,"bin_width":1.46484375,"dummy":15,"file":"../sounds/chirp16.wav","fft_size":2048,"trial_type":"latency-test","trial_index":176,"time_elapsed":400241,"internal_node_id":"0.0-1.0-1.87"},{"rt":null,"stimulus":"+","response":null,"trial_type":"html-keyboard-response","trial_index":177,"time_elapsed":400749,"internal_node_id":"0.0-1.0-0.88"},{"fs":48000,"latency":27.099609375,"f_max":16000,"bin_width":1.46484375,"dummy":26,"file":"../sounds/chirp16.wav","fft_size":2048,"trial_type":"latency-test","trial_index":178,"time_elapsed":404764,"internal_node_id":"0.0-1.0-1.88"},{"rt":null,"stimulus":"+","response":null,"trial_type":"html-keyboard-response","trial_index":179,"time_elapsed":405269,"internal_node_id":"0.0-1.0-0.89"},{"fs":48000,"latency":84.228515625,"f_max":16000,"bin_width":1.46484375,"dummy":84,"file":"../sounds/chirp16.wav","fft_size":2048,"trial_type":"latency-test","trial_index":180,"time_elapsed":409280,"internal_node_id":"0.0-1.0-1.89"},{"rt":null,"stimulus":"+","response":null,"trial_type":"html-keyboard-response","trial_index":181,"time_elapsed":409785,"internal_node_id":"0.0-1.0-0.90"},{"fs":48000,"latency":62.255859375,"f_max":16000,"bin_width":1.46484375,"dummy":61,"file":"../sounds/chirp16.wav","fft_size":2048,"trial_type":"latency-test","trial_index":182,"time_elapsed":413798,"internal_node_id":"0.0-1.0-1.90"},{"rt":null,"stimulus":"+","response":null,"trial_type":"html-keyboard-response","trial_index":183,"time_elapsed":414302,"internal_node_id":"0.0-1.0-0.91"},{"fs":48000,"latency":31.494140625,"f_max":16000,"bin_width":1.46484375,"dummy":31,"file":"../sounds/chirp16.wav","fft_size":2048,"trial_type":"latency-test","trial_index":184,"time_elapsed":418330,"internal_node_id":"0.0-1.0-1.91"},{"rt":null,"stimulus":"+","response":null,"trial_type":"html-keyboard-response","trial_index":185,"time_elapsed":418838,"internal_node_id":"0.0-1.0-0.92"},{"fs":48000,"latency":10.986328125,"f_max":16000,"bin_width":1.46484375,"dummy":10,"file":"../sounds/chirp16.wav","fft_size":2048,"trial_type":"latency-test","trial_index":186,"time_elapsed":422885,"internal_node_id":"0.0-1.0-1.92"},{"rt":null,"stimulus":"+","response":null,"trial_type":"html-keyboard-response","trial_index":187,"time_elapsed":423388,"internal_node_id":"0.0-1.0-0.93"},{"fs":48000,"latency":8.056640625,"f_max":16000,"bin_width":1.46484375,"dummy":8,"file":"../sounds/chirp16.wav","fft_size":2048,"trial_type":"latency-test","trial_index":188,"time_elapsed":427394,"internal_node_id":"0.0-1.0-1.93"},{"rt":null,"stimulus":"+","response":null,"trial_type":"html-keyboard-response","trial_index":189,"time_elapsed":427897,"internal_node_id":"0.0-1.0-0.94"},{"fs":48000,"latency":62.255859375,"f_max":16000,"bin_width":1.46484375,"dummy":62,"file":"../sounds/chirp16.wav","fft_size":2048,"trial_type":"latency-test","trial_index":190,"time_elapsed":431933,"internal_node_id":"0.0-1.0-1.94"},{"rt":null,"stimulus":"+","response":null,"trial_type":"html-keyboard-response","trial_index":191,"time_elapsed":432439,"internal_node_id":"0.0-1.0-0.95"},{"fs":48000,"latency":76.904296875,"f_max":16000,"bin_width":1.46484375,"dummy":76,"file":"../sounds/chirp16.wav","fft_size":2048,"trial_type":"latency-test","trial_index":192,"time_elapsed":436451,"internal_node_id":"0.0-1.0-1.95"},{"rt":null,"stimulus":"+","response":null,"trial_type":"html-keyboard-response","trial_index":193,"time_elapsed":436960,"internal_node_id":"0.0-1.0-0.96"},{"fs":48000,"latency":19.775390625,"f_max":16000,"bin_width":1.46484375,"dummy":19,"file":"../sounds/chirp16.wav","fft_size":2048,"trial_type":"latency-test","trial_index":194,"time_elapsed":440986,"internal_node_id":"0.0-1.0-1.96"},{"rt":null,"stimulus":"+","response":null,"trial_type":"html-keyboard-response","trial_index":195,"time_elapsed":441492,"internal_node_id":"0.0-1.0-0.97"},{"fs":48000,"latency":30.029296875,"f_max":16000,"bin_width":1.46484375,"dummy":30,"file":"../sounds/chirp16.wav","fft_size":2048,"trial_type":"latency-test","trial_index":196,"time_elapsed":445539,"internal_node_id":"0.0-1.0-1.97"},{"rt":null,"stimulus":"+","response":null,"trial_type":"html-keyboard-response","trial_index":197,"time_elapsed":446044,"internal_node_id":"0.0-1.0-0.98"},{"fs":48000,"latency":71.044921875,"f_max":16000,"bin_width":1.46484375,"dummy":70,"file":"../sounds/chirp16.wav","fft_size":2048,"trial_type":"latency-test","trial_index":198,"time_elapsed":450059,"internal_node_id":"0.0-1.0-1.98"}]